noctua_mcp/__init__.py
noctua_mcp/_version.py
noctua_mcp/cli.py
noctua_mcp/mcp_server.py
noctua_mcp/guidelines/DNA-binding_transcription_factor_activity_annotation_guidelines.md
noctua_mcp/guidelines/E3_ubiquitin_ligases.md
noctua_mcp/guidelines/GO-CAM_annotation_guidelines_README.md
noctua_mcp/guidelines/GO-CAM_modelling_guidelines_TO_DO.md
noctua_mcp/guidelines/How_to_annotate_complexes_in_GO-CAM.md
noctua_mcp/guidelines/How_to_annotate_molecular_adaptors.md
noctua_mcp/guidelines/How_to_annotate_sequestering_proteins.md
noctua_mcp/guidelines/Molecular_adaptor_activity.md
noctua_mcp/guidelines/Molecular_carrier_activity.md
noctua_mcp/guidelines/Protein_sequestering_activity.md
noctua_mcp/guidelines/Signaling_receptor_activity_annotation_guidelines.md
noctua_mcp/guidelines/Transcription_coregulator_activity.md
noctua_mcp/guidelines/Transporter_activity_annotation_annotation_guidelines.md
noctua_mcp/guidelines/WIP_-_Regulation_and_Regulatory_Processes_in_GO-CAM.md
noctua_mcp-0.2.0.dist-info/METADATA
noctua_mcp-0.2.0.dist-info/WHEEL
noctua_mcp-0.2.0.dist-info/entry_points.txt
noctua_mcp-0.2.0.dist-info/licenses/LICENSE
noctua_mcp-0.2.0.dist-info/RECORD
