Metadata-Version: 2.4
Name: noctua_mcp
Version: 0.2.0
Summary: MCP server for Barista to control Noctua editing
Author-email: My Name <my-name@my-org.org>
License-Expression: BSD-3-Clause
License-File: LICENSE
Requires-Python: <4.0,>=3.10
Requires-Dist: fastapi>=0.119.0
Requires-Dist: fastmcp>=2.12.4
Requires-Dist: linkml-runtime>=1.9.4
Requires-Dist: noctua>=0.1.2
Requires-Dist: pytest-asyncio>=0.23
Requires-Dist: typer>=0.9.0
Requires-Dist: uvicorn>=0.37.0
